toolz-stubs/__init__.pyi
toolz-stubs/dicttoolz.pyi
toolz-stubs/functoolz.pyi
toolz-stubs/itertoolz.pyi
toolz-stubs/py.typed
toolz-stubs/recipes.pyi
toolz-stubs/utils.pyi
toolz-stubs/curried/__init__.pyi
toolz-stubs/curried/exceptions.pyi
toolz-stubs/curried/operator.pyi
toolz-stubs/sandbox/__init__.pyi
toolz-stubs/sandbox/core.pyi
toolz-stubs/sandbox/parallel.pyi
tlz-stubs/__init__.pyi
tlz-stubs/dicttoolz.pyi
tlz-stubs/functoolz.pyi
tlz-stubs/itertoolz.pyi
tlz-stubs/py.typed
tlz-stubs/recipes.pyi
tlz-stubs/utils.pyi
tlz-stubs/curried/__init__.pyi
tlz-stubs/curried/exceptions.pyi
tlz-stubs/curried/operator.pyi
tlz-stubs/sandbox/__init__.pyi
tlz-stubs/sandbox/core.pyi
tlz-stubs/sandbox/parallel.pyi
toolz_stubs-0.3.1.dist-info/METADATA
toolz_stubs-0.3.1.dist-info/WHEEL
toolz_stubs-0.3.1.dist-info/licenses/LICENSE
toolz_stubs-0.3.1.dist-info/RECORD
