Metadata-Version: 2.4
Name: toolz-stubs
Version: 0.3.1
Summary: Type stubs for toolz
Project-URL: Homepage, https://github.com/mgrinshpon/toolz-stubs
Project-URL: Repository, https://github.com/mgrinshpon/toolz-stubs
Project-URL: Issues, https://github.com/mgrinshpon/toolz-stubs/issues
Author-email: Michael Grinshpon <mgrinshpon@gmail.com>
License-Expression: BSD-3-Clause
License-File: LICENSE
Keywords: cytoolz,functional,stubs,tlz,toolz,type hints,typing
Classifier: Development Status :: 4 - Beta
Classifier: Intended Audience :: Developers
Classifier: License :: OSI Approved :: BSD License
Classifier: Programming Language :: Python :: 3
Classifier: Programming Language :: Python :: 3.12
Classifier: Programming Language :: Python :: 3.13
Classifier: Programming Language :: Python :: 3.14
Classifier: Typing :: Stubs Only
Requires-Python: >=3.12
Requires-Dist: toolz~=1.0
Requires-Dist: typing-extensions>=4.10; python_version < '3.13'
